miat/__init__.py
miat/_version.py
miat/tools.py
miat/icons/add_1_circles_icon.png
miat/icons/add_1_circles_icon_large.png
miat/icons/add_1_hbar_icon.png
miat/icons/add_1_hbar_icon_large.png
miat/icons/add_1_vbar_icon.png
miat/icons/add_1_vbar_icon_large.png
miat/icons/add_2_circles_icon.png
miat/icons/add_2_circles_icon_large.png
miat/icons/add_2_hbar_icon.png
miat/icons/add_2_hbar_icon_large.png
miat/icons/add_2_vbar_icon.png
miat/icons/add_2_vbar_icon_large.png
miat/icons/add_3_circles_icon.png
miat/icons/add_3_circles_icon_large.png
miat/icons/add_3_hbar_icon.png
miat/icons/add_3_hbar_icon_large.png
miat/icons/add_3_vbar_icon.png
miat/icons/add_3_vbar_icon_large.png
miat/icons/remove_1_circles_icon.png
miat/icons/remove_1_circles_icon_large.png
miat/icons/remove_1_hbar_icon.png
miat/icons/remove_1_hbar_icon_large.png
miat/icons/remove_1_vbar_icon.png
miat/icons/remove_1_vbar_icon_large.png
miat/icons/remove_2_circles_icon.png
miat/icons/remove_2_circles_icon_large.png
miat/icons/remove_2_hbar_icon.png
miat/icons/remove_2_hbar_icon_large.png
miat/icons/remove_2_vbar_icon.png
miat/icons/remove_2_vbar_icon_large.png
miat/icons/remove_3_circles_icon.png
miat/icons/remove_3_circles_icon_large.png
miat/icons/remove_3_hbar_icon.png
miat/icons/remove_3_hbar_icon_large.png
miat/icons/remove_3_vbar_icon.png
miat/icons/remove_3_vbar_icon_large.png
miat-0.16.3.dist-info/LICENSE
miat-0.16.3.dist-info/METADATA
miat-0.16.3.dist-info/WHEEL
miat-0.16.3.dist-info/top_level.txt
miat-0.16.3.dist-info/RECORD
