Metadata-Version: 2.1
Name: miat
Version: 0.16.3
Summary: Basic python manual image analysis tool using matplotlib
Home-page: https://github.com/CephalonAhmes/miat
Author: Philippe Desmarais
Author-email: philippe.desmarais0trash@gmail.com
License: MIT
Platform: UNKNOWN
Requires-Python: >=3.6
Requires-Dist: matplotlib (>=3.0.0)
Requires-Dist: numpy (>=1.17.0)
